Kalkulus8/__init__.py
Kalkulus8/limit/__init__.py
Kalkulus8/limit/module_limit.py
Kalkulus8-0.1.0.dist-info/METADATA
Kalkulus8-0.1.0.dist-info/WHEEL
Kalkulus8-0.1.0.dist-info/top_level.txt
Kalkulus8-0.1.0.dist-info/RECORD
