Metadata-Version: 2.1
Name: Kalkulus8
Version: 0.1.0
Summary: Paket ini terdiri dari beberapa modul yang berfungsi untuk menganalisis berbagai inputan dalam lingkup kalkulus
Home-page: https://github.com/indirarara/CalculusPython8.git
Author: Kelompok 8 AP B
Author-email: indiraramayani9@gmail.com
Classifier: Programming Language :: Python :: 3
Classifier: License :: OSI Approved :: MIT License
Classifier: Operating System :: OS Independent
Requires-Python: >=3.6
Requires-Dist: numpy >=1.20
Requires-Dist: matplotlib >=3.3
Requires-Dist: sympy >=1.8
